backports/__init__.py
backports/method_request.py
backports.method_request-1.2.dist-info/DESCRIPTION.rst
backports.method_request-1.2.dist-info/METADATA
backports.method_request-1.2.dist-info/RECORD
backports.method_request-1.2.dist-info/WHEEL
backports.method_request-1.2.dist-info/metadata.json
backports.method_request-1.2.dist-info/top_level.txt
