Metadata-Version: 1.2
Name: backports.method-request
Version: 1.2
Summary: backports.method_request
Home-page: https://github.com/jaraco/backports.method_request
Author: Jason R. Coombs
Author-email: jaraco@jaraco.com
License: UNKNOWN
Platform: UNKNOWN
Classifier: Development Status :: 5 - Production/Stable
Classifier: Intended Audience :: Developers
Classifier: License :: OSI Approved :: MIT License
Classifier: Programming Language :: Python :: 2.6
Classifier: Programming Language :: Python :: 2.7
Classifier: Programming Language :: Python :: 3
Requires-Python: >=2.6
